nmap_vscan/__init__.py
nmap_vscan/vscan.py
nmap_vscan_fix-1.2.0.dist-info/LICENSE
nmap_vscan_fix-1.2.0.dist-info/METADATA
nmap_vscan_fix-1.2.0.dist-info/WHEEL
nmap_vscan_fix-1.2.0.dist-info/top_level.txt
nmap_vscan_fix-1.2.0.dist-info/RECORD
