Metadata-Version: 2.1
Name: nmap-vscan-fix
Version: 1.2.0
Summary: nmap service and application version detection (without nmap installation)
Author: An0m
Author-email: 
License: MIT
Keywords: nmap vscan fingerprint recognition security
Classifier: Development Status :: 2 - Pre-Alpha
Classifier: Intended Audience :: System Administrators
Classifier: Programming Language :: Python :: 2 :: Only
Classifier: License :: OSI Approved :: MIT License
Classifier: Operating System :: OS Independent
License-File: LICENSE
